connectivity/__init__.py
connectivity/config/README.md
connectivity/config/__init__.py
connectivity/config/default.json
connectivity/config/logging.py
connectivity/config/logging_template.py
connectivity/constants.py
connectivity/main.py
connectivity/src/drivers/__init__.py
connectivity/src/drivers/ping.py
connectivity/src/drivers/sds011.py
connectivity/src/feeders/__init__.py
connectivity/src/feeders/datalog_feeder.py
connectivity/src/feeders/frontier_datalog.py
connectivity/src/feeders/ifeeder.py
connectivity/src/feeders/pinning_services/__init__.py
connectivity/src/feeders/pinning_services/gateways/__init__.py
connectivity/src/feeders/pinning_services/gateways/crust.py
connectivity/src/feeders/pinning_services/gateways/local.py
connectivity/src/feeders/pinning_services/gateways/pinata.py
connectivity/src/feeders/pinning_services/gateways/pinning_gateway.py
connectivity/src/feeders/pinning_services/gateways/temporal.py
connectivity/src/feeders/pinning_services/pinning_manager.py
connectivity/src/feeders/robonomics_feeder.py
connectivity/src/sensors/__init__.py
connectivity/src/sensors/sensors_fabric.py
connectivity/src/sensors/sensors_types/__init__.py
connectivity/src/sensors/sensors_types/altruist.py
connectivity/src/sensors/sensors_types/base.py
connectivity/src/sensors/sensors_types/environmental_box.py
connectivity/src/sensors/sensors_types/lora_sensors.py
connectivity/src/sensors/sensors_types/mobile_lab.py
connectivity/src/sensors/sensors_types/sensor_sds011.py
connectivity/src/sensors/sensors_types/sensor_template.py
connectivity/src/sensors/sensors_types/trackagro_sensor.py
connectivity/src/stations/__init__.py
connectivity/src/stations/comstation.py
connectivity/src/stations/httpstation.py
connectivity/src/stations/istation.py
connectivity/src/stations/mqttstation.py
connectivity/src/stations/trackargostation.py
connectivity/utils/__init__.py
connectivity/utils/database.py
connectivity/utils/datalog_db.py
connectivity/utils/datalog_payload.py
sensors_connectivity-1.6.9.dist-info/LICENSE
sensors_connectivity-1.6.9.dist-info/METADATA
sensors_connectivity-1.6.9.dist-info/WHEEL
sensors_connectivity-1.6.9.dist-info/entry_points.txt
sensors_connectivity-1.6.9.dist-info/RECORD
