Metadata-Version: 2.3
Name: sensors_connectivity
Version: 1.6.9
Summary: Robonomics package to read data from sensors and publish to different output channels
License: BSD 3-Clause License
Author: Vadim Manaenko
Author-email: vadim.razorq@gmail.com
Requires-Python: >=3.10,<4.0
Classifier: License :: Other/Proprietary License
Classifier: Programming Language :: Python :: 3
Classifier: Programming Language :: Python :: 3.10
Classifier: Programming Language :: Python :: 3.11
Classifier: Programming Language :: Python :: 3.12
Classifier: Programming Language :: Python :: 3.13
Requires-Dist: IPFS-Toolkit (>=0.4.4,<0.5.0)
Requires-Dist: crust-interface-patara (>=0.1.1,<0.2.0)
Requires-Dist: ipfshttpclient (==0.8.0a2)
Requires-Dist: netifaces (>=0.11.0,<0.12.0)
Requires-Dist: paho-mqtt (>=1.6.1,<2.0.0)
Requires-Dist: pinatapy-vourhey (>=0.1.3,<0.2.0)
Requires-Dist: prometheus-client (>=0.13.1,<0.14.0)
Requires-Dist: py-sr25519-bindings (>=0.2.0,<0.3.0)
Requires-Dist: pynacl (>=1.5.0,<2.0.0)
Requires-Dist: pyserial (>=3.5,<4.0)
Requires-Dist: pyyaml (>=6.0,<7.0)
Requires-Dist: requests (>=2.27.1,<3.0.0)
Requires-Dist: robonomics-interface (>=1.6.0,<2.0.0)
Requires-Dist: sentry_sdk (==2.8.0)
Project-URL: Repository, https://github.com/airalab/sensors-connectivity
